Metadata-Version: 1.0
Name: ConfigObject
Version: 0.1
Summary: ConfigObject is a wrapper to the python ConfigParser to
Home-page: http://www.gawel.org/docs/ConfigObject/index.html
Author: Gael Pasgrimaud
Author-email: gael@gawel.org
License: GPL
Keywords: configuration config
Platform: UNKNOWN
Classifier: Intended Audience :: Developers
Classifier: License :: OSI Approved :: GNU General Public License (GPL)
Classifier: Operating System :: OS Independent
Classifier: Topic :: Software Development :: Libraries :: Python Modules
